[
    {"A": {
        "collect_start_time": false,
        "collect_end_date": false,
        "collect_end_time": false,
        "pump_rate": false,
        "imr":true,
        "fmr":true,
        "tvs": false,
        "vol_post_dilution_ul": true,
        "filter_type": false,
        "filt_bornon_date": true,
        "air_subsample_vol_ml": false,
        "elute_date": true,
        "elute_notes": true,
        "tech_init": true,
        "init_vol" : true,

        "samp_vol_filt": null,
        "sample_loc_type" : null,
        "samp_env_type" : null ,
        "water_type" : null,
        "tvs_units":null ,
        "tvs_stage": null,
        "tvs_liters": null,
        "arrive_notes": null,   
    }},
    {"F":{
        "collect_start_time": true,
        "collect_end_date": true,
        "collect_end_time": true,
        "pump_rate": true,
        "imr":true,
        "fmr":true,
        "tvs": false,
        "vol_post_dilution_ul": true,
        "filter_type": true,
        "filt_bornon_date": true,
        "air_subsample_vol_ml": true,
        "elute_date": false,
        "elute_notes": false,
        "tech_init": false,
        "init_vol" : false, 
    }},
    {"LM": {
        "collect_start_time": true,
        "collect_end_date": true,
        "collect_end_time": true,
        "pump_rate": true,
        "imr":true,
        "fmr":true,
        "tvs": true,
        "vol_post_dilution_ul": true,
        "filter_type": true,
        "filt_bornon_date": true,
        "air_subsample_vol_ml": true,
        "elute_date": true,
        "elute_notes": true,
        "tech_init": true,
        "init_vol" : true,
    }},
    {"SM": {
        "collect_start_time": true,
        "collect_end_date": true,
        "collect_end_time": true,
        "pump_rate": true,
        "imr":true,
        "fmr":true,
        "tvs": false,
        "vol_post_dilution_ul": false,
        "filter_type": true,
        "filt_bornon_date": true,
        "air_subsample_vol_ml": true,
        "elute_date": true,
        "elute_notes": true,
        "tech_init": true,
        "init_vol" : true,
    }},
    {"WW": {
        "collect_start_time": false,
        "collect_end_date": false,
        "collect_end_time": false,
        "pump_rate": true,
        "imr":true,
        "fmr":true,
        "tvs": false,
        "vol_post_dilution_ul": true,
        "filter_type": true,
        "filt_bornon_date": true,
        "air_subsample_vol_ml": true,
        "elute_date": true,
        "elute_notes": true,
        "tech_init": true,
        "init_vol" : true,
    }},
    {"W":{
        "collect_start_time": false,
        "collect_end_date": false,
        "collect_end_time": false,
        "pump_rate": true,
        "imr":false,
        "fmr":false,
        "tvs": false,
        "vol_post_dilution_ul": true,
        "filter_type": false,
        "filt_bornon_date": false,
        "air_subsample_vol_ml": true,
        "elute_date": false,
        "elute_notes": false,
        "tech_init": false,
        "init_vol" : false, 
    }},
]
    
